README.txt
setup.py
wclog/__init__.py
wclog/config.py
wclog/wclog.py
wclog.egg-info/PKG-INFO
wclog.egg-info/SOURCES.txt
wclog.egg-info/dependency_links.txt
wclog.egg-info/top_level.txt