Metadata-Version: 1.1
Name: wclog
Version: 0.1.1
Summary: wechat controller: client part
Home-page: http://github.com/zhoulinjun1994
Author: zhoulinjun
Author-email: zhoulinjun1994@163.com
License: BSD License
Platform: all
Classifier: Programming Language :: Python
Classifier: Programming Language :: Python :: 2
Classifier: Programming Language :: Python :: 2.7
